CHANGELOG.md
LICENSE
MANIFEST.in
README.md
setup.py
sorl_watermark.egg-info/PKG-INFO
sorl_watermark.egg-info/SOURCES.txt
sorl_watermark.egg-info/dependency_links.txt
sorl_watermark.egg-info/requires.txt
sorl_watermark.egg-info/top_level.txt
sorl_watermarker/__init__.py
sorl_watermarker/models.py
sorl_watermarker/parsers.py
sorl_watermarker/conf/__init__.py
sorl_watermarker/conf/defaults.py
sorl_watermarker/engines/__init__.py
sorl_watermarker/engines/base.py
sorl_watermarker/engines/pgmagick_engine.py
sorl_watermarker/engines/pil_engine.py
tests/__init__.py
tests/runtests.py
tests/engines/__init__.py
tests/engines/base_case.py
tests/engines/pgmagick_test.py
tests/engines/pil_test.py