Metadata-Version: 2.1
Name: sorl-watermark
Version: 1.2.0
Summary: Image based watermarks for sorl-thumbnail
Home-page: https://github.com/originell/sorl-watermark
Author: Luis Nell
Author-email: luis@originell.org
License: UNKNOWN
Platform: any
Classifier: Development Status :: 6 - Mature
Classifier: Environment :: Web Environment
Classifier: Framework :: Django
Classifier: Intended Audience :: Developers
Classifier: License :: OSI Approved :: MIT License
Classifier: Operating System :: OS Independent
Classifier: Programming Language :: Python
Classifier: Programming Language :: Python :: 3
Classifier: Topic :: Internet :: WWW/HTTP :: Dynamic Content
Classifier: Topic :: Multimedia :: Graphics
